src/ALU.v
`timescale 1ns / 1ps

module ALU(
    input [3:0] alufn,
    input [31:0] A,
    input [31:0] B,
    output reg [31:0] Y
);

    always @(*) begin
        case(alufn)
            4'b0000: Y = A + B;
            4'b0001: Y = A - B;
            4'b0100: Y = (A == B) ? 32'd1 : 32'd0;
            4'b0101: Y = ($signed(A) < $signed(B)) ? 32'd1 : 32'd0;
            4'b0110: Y = ($signed(A) <= $signed(B)) ? 32'd1 : 32'd0;
            4'b1000: Y = A & B;
            4'b1001: Y = A | B;
            4'b1010: Y = A ^ B;
            4'b1011: Y = ~(A ^ B);
            4'b1100: Y = A << B[4:0];
            4'b1101: Y = A >> B[4:0];
            4'b1111: Y = $signed(A) >>> B[4:0];
            default: Y = A + B;
        endcase
    end

endmodule

sim/ALU_tb.v
`timescale 1ns / 1ps

module tb_ALU;

    reg [3:0] alufn;
    reg [31:0] A;
    reg [31:0] B;
    wire [31:0] Y;

    ALU dut (
        .alufn(alufn),
        .A(A),
        .B(B),
        .Y(Y)
    );

    task check;
        input [3:0] fn;
        input [31:0] a_in;
        input [31:0] b_in;
        input [31:0] expected;
        input [160:0] name;
        begin
            alufn = fn;
            A = a_in;
            B = b_in;
            #10;

            if (Y !== expected) begin
                $display("FAIL %s", name);
                $display("alufn=%b A=%h B=%h expected=%h got=%h", alufn, A, B, expected, Y);
            end else begin
                $display("PASS %s", name);
            end
        end
    endtask

    initial begin
        $dumpfile("alu.vcd");
        $dumpvars(0, tb_ALU);

        check(4'b0000, 32'd10, 32'd5, 32'd15, "ADD");
        check(4'b0001, 32'd10, 32'd5, 32'd5, "SUB");

        check(4'b0100, 32'd10, 32'd10, 32'd1, "CMPEQ true");
        check(4'b0100, 32'd10, 32'd5, 32'd0, "CMPEQ false");

        check(4'b0101, 32'd5, 32'd10, 32'd1, "CMPLT true");
        check(4'b0101, 32'd10, 32'd5, 32'd0, "CMPLT false");
        check(4'b0101, 32'hFFFF_FFFF, 32'd1, 32'd1, "CMPLT signed negative");

        check(4'b0110, 32'd5, 32'd5, 32'd1, "CMPLE equal");
        check(4'b0110, 32'd5, 32'd10, 32'd1, "CMPLE less");
        check(4'b0110, 32'd10, 32'd5, 32'd0, "CMPLE false");

        check(4'b1000, 32'hF0F0_F0F0, 32'h0F0F_0F0F, 32'h0000_0000, "AND");
        check(4'b1001, 32'hF0F0_F0F0, 32'h0F0F_0F0F, 32'hFFFF_FFFF, "OR");
        check(4'b1010, 32'hAAAA_AAAA, 32'h5555_5555, 32'hFFFF_FFFF, "XOR");
        check(4'b1011, 32'hAAAA_AAAA, 32'h5555_5555, 32'h0000_0000, "XNOR");

        check(4'b1100, 32'h0000_0001, 32'd4, 32'h0000_0010, "SHL");
        check(4'b1101, 32'h8000_0000, 32'd4, 32'h0800_0000, "SHR");
        check(4'b1111, 32'h8000_0000, 32'd4, 32'hF800_0000, "SRA");

        check(4'b1100, 32'h0000_0001, 32'd31, 32'h8000_0000, "SHL by 31");
        check(4'b1101, 32'h8000_0000, 32'd31, 32'h0000_0001, "SHR by 31");
        check(4'b1111, 32'h8000_0000, 32'd31, 32'hFFFF_FFFF, "SRA by 31");

        check(4'b0010, 32'd7, 32'd8, 32'd15, "default ADD");

        $display("ALU test completed");
        $finish;
    end

endmodule

Beta_Processor.sim/sim_1/behav/xsim/alu.vcd
$date
   Fri Jun 26 22:10:18 2026
$end

$version
  2024.2.0
  $dumpfile ("alu.vcd") 
$end

$timescale
  1ps
$end

$scope module tb_ALU $end
$var reg 4 ! alufn [3:0] $end
$var reg 32 " A [31:0] $end
$var reg 32 # B [31:0] $end
$var wire 32 $ Y [31:0] $end
$scope module dut $end
$var wire 4 % alufn [3:0] $end
$var wire 32 & A [31:0] $end
$var wire 32 ' B [31:0] $end
$var reg 32 ( Y [31:0] $end
$upscope $end
$scope task check $end
$var reg 4 ) fn [3:0] $end
$var reg 32 * a_in [31:0] $end
$var reg 32 + b_in [31:0] $end
$var reg 32 , expected [31:0] $end
$var reg 161 - name [160:0] $end
$upscope $end
$upscope $end
$enddefinitions $end

#0
$dumpvars
b0 !
b1010 "
b101 #
b1111 $
b0 %
b1010 &
b101 '
b1111 (
b0 )
b1010 *
b101 +
b1111 ,
b10000010100010001000100 -
$end

#10000
b1 !
b101 $
b1 %
b101 (
b1 )
b101 ,
b10100110101010101000010 -

#20000
b100 !
b1010 #
b1 $
b100 %
b1010 '
b1 (
b100 )
b1010 +
b1 ,
b1000011010011010101000001000101010100010010000001110100011100100111010101100101 -

#30000
b101 #
b0 $
b101 '
b0 (
b101 +
b0 ,
b100001101001101010100000100010101010001001000000110011001100001011011000111001101100101 -

#40000
b101 !
b101 "
b1010 #
b1 $
b101 %
b101 &
b1010 '
b1 (
b101 )
b101 *
b1010 +
b1 ,
b1000011010011010101000001001100010101000010000001110100011100100111010101100101 -

#50000
b1010 "
b101 #
b0 $
b1010 &
b101 '
b0 (
b1010 *
b101 +
b0 ,
b100001101001101010100000100110001010100001000000110011001100001011011000111001101100101 -

#60000
b11111111111111111111111111111111 "
b1 #
b1 $
b11111111111111111111111111111111 &
b1 '
b1 (
b11111111111111111111111111111111 *
b1 +
b1 ,
b10100110101010000010011000101010000100000011100110110100101100111011011100110010101100100001000000110111001100101011001110110000101110100011010010111011001100101 -

#70000
b110 !
b101 "
b101 #
b110 %
b101 &
b101 '
b110 )
b101 *
b101 +
b100001101001101010100000100110001000101001000000110010101110001011101010110000101101100 -

#80000
b1010 #
b1010 '
b1010 +
b1000011010011010101000001001100010001010010000001101100011001010111001101110011 -

#90000
b1010 "
b101 #
b0 $
b1010 &
b101 '
b0 (
b1010 *
b101 +
b0 ,
b100001101001101010100000100110001000101001000000110011001100001011011000111001101100101 -

#100000
b1000 !
b11110000111100001111000011110000 "
b1111000011110000111100001111 #
b1000 %
b11110000111100001111000011110000 &
b1111000011110000111100001111 '
b1000 )
b11110000111100001111000011110000 *
b1111000011110000111100001111 +
b10000010100111001000100 -

#110000
b1001 !
b11111111111111111111111111111111 $
b1001 %
b11111111111111111111111111111111 (
b1001 )
b11111111111111111111111111111111 ,
b100111101010010 -

#120000
b1010 !
b10101010101010101010101010101010 "
b1010101010101010101010101010101 #
b1010 %
b10101010101010101010101010101010 &
b1010101010101010101010101010101 '
b1010 )
b10101010101010101010101010101010 *
b1010101010101010101010101010101 +
b10110000100111101010010 -

#130000
b1011 !
b0 $
b1011 %
b0 (
b1011 )
b0 ,
b1011000010011100100111101010010 -

#140000
b1100 !
b1 "
b100 #
b10000 $
b1100 %
b1 &
b100 '
b10000 (
b1100 )
b1 *
b100 +
b10000 ,
b10100110100100001001100 -

#150000
b1101 !
b10000000000000000000000000000000 "
b1000000000000000000000000000 $
b1101 %
b10000000000000000000000000000000 &
b1000000000000000000000000000 (
b1101 )
b10000000000000000000000000000000 *
b1000000000000000000000000000 ,
b10100110100100001010010 -

#160000
b1111 !
b11111000000000000000000000000000 $
b1111 %
b11111000000000000000000000000000 (
b1111 )
b11111000000000000000000000000000 ,
b10100110101001001000001 -

#170000
b1100 !
b1 "
b11111 #
b10000000000000000000000000000000 $
b1100 %
b1 &
b11111 '
b10000000000000000000000000000000 (
b1100 )
b1 *
b11111 +
b10000000000000000000000000000000 ,
b10100110100100001001100001000000110001001111001001000000011001100110001 -

#180000
b1101 !
b10000000000000000000000000000000 "
b1 $
b1101 %
b10000000000000000000000000000000 &
b1 (
b1101 )
b10000000000000000000000000000000 *
b1 ,
b10100110100100001010010001000000110001001111001001000000011001100110001 -

#190000
b1111 !
b11111111111111111111111111111111 $
b1111 %
b11111111111111111111111111111111 (
b1111 )
b11111111111111111111111111111111 ,
b10100110101001001000001001000000110001001111001001000000011001100110001 -

#200000
b10 !
b111 "
b1000 #
b1111 $
b10 %
b111 &
b1000 '
b1111 (
b10 )
b111 *
b1000 +
b1111 ,
b110010001100101011001100110000101110101011011000111010000100000010000010100010001000100 -
