Beta_Processor.srcs/sources_1/new/Control_unit.v
`timescale 1ns / 1ps


module Control_unit(
    input wire z,
    input wire [5:0] op,
    output reg [3:0] alufn,
    output reg [1:0] wdsel,
    output reg [1:0] pcsel,
    output reg ra2sel,
    output reg asel,
    output reg bsel,
    output reg moe,
    output reg mwr,
    output reg werf
);

    always @(*) begin
        pcsel  = 2'b00;
        ra2sel = 1'b0;
        asel   = 1'b0;
        bsel   = 1'b0;
        moe    = 1'b0;
        mwr    = 1'b0;
        wdsel  = 2'b00;
        werf   = 1'b0;
        alufn  = 4'b0000;

        case(op[5:4])

            2'b10: begin
                pcsel  = 2'b00;
                ra2sel = 1'b0;
                asel   = 1'b0;
                bsel   = 1'b0;
                moe    = 1'b0;
                mwr    = 1'b0;
                wdsel  = 2'b01;
                werf   = 1'b1;

                case(op[3:0])
                    4'b0000: alufn = 4'b0000;
                    4'b0001: alufn = 4'b0001;
                    4'b0100: alufn = 4'b0100;
                    4'b0101: alufn = 4'b0101;
                    4'b0110: alufn = 4'b0110;
                    4'b1000: alufn = 4'b1000;
                    4'b1001: alufn = 4'b1001;
                    4'b1010: alufn = 4'b1010;
                    4'b1011: alufn = 4'b1011;
                    4'b1100: alufn = 4'b1100;
                    4'b1101: alufn = 4'b1101;
                    4'b1111: alufn = 4'b1111;
                    default: begin
                        alufn = 4'b0000;
                        werf  = 1'b0;
                    end
                endcase
            end

            2'b11: begin
                pcsel  = 2'b00;
                ra2sel = 1'b0;
                asel   = 1'b0;
                bsel   = 1'b1;
                moe    = 1'b0;
                mwr    = 1'b0;
                wdsel  = 2'b01;
                werf   = 1'b1;

                case(op[3:0])
                    4'b0000: alufn = 4'b0000;
                    4'b0001: alufn = 4'b0001;
                    4'b0100: alufn = 4'b0100;
                    4'b0101: alufn = 4'b0101;
                    4'b0110: alufn = 4'b0110;
                    4'b1000: alufn = 4'b1000;
                    4'b1001: alufn = 4'b1001;
                    4'b1010: alufn = 4'b1010;
                    4'b1011: alufn = 4'b1011;
                    4'b1100: alufn = 4'b1100;
                    4'b1101: alufn = 4'b1101;
                    4'b1111: alufn = 4'b1111;
                    default: begin
                        alufn = 4'b0000;
                        werf  = 1'b0;
                    end
                endcase
            end

            2'b01: begin
                case(op[3:0])

                    4'b1000: begin
                        pcsel  = 2'b00;
                        ra2sel = 1'b0;
                        asel   = 1'b0;
                        bsel   = 1'b1;
                        moe    = 1'b1;
                        mwr    = 1'b0;
                        wdsel  = 2'b10;
                        werf   = 1'b1;
                        alufn  = 4'b0000;
                    end

                    4'b1001: begin
                        pcsel  = 2'b00;
                        ra2sel = 1'b1;
                        asel   = 1'b0;
                        bsel   = 1'b1;
                        moe    = 1'b0;
                        mwr    = 1'b1;
                        wdsel  = 2'b00;
                        werf   = 1'b0;
                        alufn  = 4'b0000;
                    end

                    4'b1111: begin
                        pcsel  = 2'b00;
                        ra2sel = 1'b0;
                        asel   = 1'b1;
                        bsel   = 1'b1;
                        moe    = 1'b1;
                        mwr    = 1'b0;
                        wdsel  = 2'b10;
                        werf   = 1'b1;
                        alufn  = 4'b0000;
                    end

                    4'b1011: begin
                        pcsel  = 2'b10;
                        ra2sel = 1'b0;
                        asel   = 1'b0;
                        bsel   = 1'b0;
                        moe    = 1'b0;
                        mwr    = 1'b0;
                        wdsel  = 2'b00;
                        werf   = 1'b1;
                        alufn  = 4'b0000;
                    end

                    4'b1100: begin
                        pcsel  = (z == 1'b1) ? 2'b01 : 2'b00;
                        ra2sel = 1'b0;
                        asel   = 1'b0;
                        bsel   = 1'b0;
                        moe    = 1'b0;
                        mwr    = 1'b0;
                        wdsel  = 2'b00;
                        werf   = (z == 1'b1) ? 1'b1 : 1'b0;
                        alufn  = 4'b0000;
                    end

                    4'b1101: begin
                        pcsel  = (z == 1'b0) ? 2'b01 : 2'b00;
                        ra2sel = 1'b0;
                        asel   = 1'b0;
                        bsel   = 1'b0;
                        moe    = 1'b0;
                        mwr    = 1'b0;
                        wdsel  = 2'b00;
                        werf   = (z == 1'b0) ? 1'b1 : 1'b0;
                        alufn  = 4'b0000;
                    end

                    default: begin
                        pcsel  = 2'b00;
                        ra2sel = 1'b0;
                        asel   = 1'b0;
                        bsel   = 1'b0;
                        moe    = 1'b0;
                        mwr    = 1'b0;
                        wdsel  = 2'b00;
                        werf   = 1'b0;
                        alufn  = 4'b0000;
                    end

                endcase
            end

            default: begin
                pcsel  = 2'b00;
                ra2sel = 1'b0;
                asel   = 1'b0;
                bsel   = 1'b0;
                moe    = 1'b0;
                mwr    = 1'b0;
                wdsel  = 2'b00;
                werf   = 1'b0;
                alufn  = 4'b0000;
            end

        endcase
    end

endmodule

sim/Control_unit_tb.v
`timescale 1ns / 1ps

module tb_Control_unit;

    reg z;
    reg [5:0] op;

    wire [3:0] alufn;
    wire [1:0] wdsel;
    wire [1:0] pcsel;
    wire ra2sel;
    wire asel;
    wire bsel;
    wire moe;
    wire mwr;
    wire werf;

    Control_unit dut (
        .z(z),
        .op(op),
        .alufn(alufn),
        .wdsel(wdsel),
        .pcsel(pcsel),
        .ra2sel(ra2sel),
        .asel(asel),
        .bsel(bsel),
        .moe(moe),
        .mwr(mwr),
        .werf(werf)
    );

    task check;
        input [5:0] op_in;
        input z_in;
        input [3:0] exp_alufn;
        input [1:0] exp_wdsel;
        input [1:0] exp_pcsel;
        input exp_ra2sel;
        input exp_asel;
        input exp_bsel;
        input exp_moe;
        input exp_mwr;
        input exp_werf;
        input [160:0] name;
        begin
            op = op_in;
            z = z_in;
            #10;

            if (
                alufn  !== exp_alufn  ||
                wdsel  !== exp_wdsel  ||
                pcsel  !== exp_pcsel  ||
                ra2sel !== exp_ra2sel ||
                asel   !== exp_asel   ||
                bsel   !== exp_bsel   ||
                moe    !== exp_moe    ||
                mwr    !== exp_mwr    ||
                werf   !== exp_werf
            ) begin
                $display("FAIL %s", name);
                $display("op=%b z=%b", op, z);
                $display("expected alufn=%b wdsel=%b pcsel=%b ra2sel=%b asel=%b bsel=%b moe=%b mwr=%b werf=%b",
                         exp_alufn, exp_wdsel, exp_pcsel, exp_ra2sel, exp_asel, exp_bsel, exp_moe, exp_mwr, exp_werf);
                $display("got      alufn=%b wdsel=%b pcsel=%b ra2sel=%b asel=%b bsel=%b moe=%b mwr=%b werf=%b",
                         alufn, wdsel, pcsel, ra2sel, asel, bsel, moe, mwr, werf);
            end else begin
                $display("PASS %s", name);
            end
        end
    endtask

    initial begin
        $dumpfile("control_unit.vcd");
        $dumpvars(0, tb_Control_unit);

        check(6'b100000, 1'b0, 4'b0000, 2'b01, 2'b00, 1'b0, 1'b0, 1'b0, 1'b0, 1'b0, 1'b1, "ADD");
        check(6'b100001, 1'b0, 4'b0001, 2'b01, 2'b00, 1'b0, 1'b0, 1'b0, 1'b0, 1'b0, 1'b1, "SUB");
        check(6'b100100, 1'b0, 4'b0100, 2'b01, 2'b00, 1'b0, 1'b0, 1'b0, 1'b0, 1'b0, 1'b1, "CMPEQ");
        check(6'b100101, 1'b0, 4'b0101, 2'b01, 2'b00, 1'b0, 1'b0, 1'b0, 1'b0, 1'b0, 1'b1, "CMPLT");
        check(6'b100110, 1'b0, 4'b0110, 2'b01, 2'b00, 1'b0, 1'b0, 1'b0, 1'b0, 1'b0, 1'b1, "CMPLE");
        check(6'b101000, 1'b0, 4'b1000, 2'b01, 2'b00, 1'b0, 1'b0, 1'b0, 1'b0, 1'b0, 1'b1, "AND");
        check(6'b101001, 1'b0, 4'b1001, 2'b01, 2'b00, 1'b0, 1'b0, 1'b0, 1'b0, 1'b0, 1'b1, "OR");
        check(6'b101010, 1'b0, 4'b1010, 2'b01, 2'b00, 1'b0, 1'b0, 1'b0, 1'b0, 1'b0, 1'b1, "XOR");
        check(6'b101011, 1'b0, 4'b1011, 2'b01, 2'b00, 1'b0, 1'b0, 1'b0, 1'b0, 1'b0, 1'b1, "XNOR");
        check(6'b101100, 1'b0, 4'b1100, 2'b01, 2'b00, 1'b0, 1'b0, 1'b0, 1'b0, 1'b0, 1'b1, "SHL");
        check(6'b101101, 1'b0, 4'b1101, 2'b01, 2'b00, 1'b0, 1'b0, 1'b0, 1'b0, 1'b0, 1'b1, "SHR");
        check(6'b101111, 1'b0, 4'b1111, 2'b01, 2'b00, 1'b0, 1'b0, 1'b0, 1'b0, 1'b0, 1'b1, "SRA");

        check(6'b110000, 1'b0, 4'b0000, 2'b01, 2'b00, 1'b0, 1'b0, 1'b1, 1'b0, 1'b0, 1'b1, "ADDC");
        check(6'b110001, 1'b0, 4'b0001, 2'b01, 2'b00, 1'b0, 1'b0, 1'b1, 1'b0, 1'b0, 1'b1, "SUBC");
        check(6'b111000, 1'b0, 4'b1000, 2'b01, 2'b00, 1'b0, 1'b0, 1'b1, 1'b0, 1'b0, 1'b1, "ANDC");
        check(6'b111001, 1'b0, 4'b1001, 2'b01, 2'b00, 1'b0, 1'b0, 1'b1, 1'b0, 1'b0, 1'b1, "ORC");
        check(6'b111010, 1'b0, 4'b1010, 2'b01, 2'b00, 1'b0, 1'b0, 1'b1, 1'b0, 1'b0, 1'b1, "XORC");

        check(6'b011000, 1'b0, 4'b0000, 2'b10, 2'b00, 1'b0, 1'b0, 1'b1, 1'b1, 1'b0, 1'b1, "LD");
        check(6'b011001, 1'b0, 4'b0000, 2'b00, 2'b00, 1'b1, 1'b0, 1'b1, 1'b0, 1'b1, 1'b0, "ST");
        check(6'b011111, 1'b0, 4'b0000, 2'b10, 2'b00, 1'b0, 1'b1, 1'b1, 1'b1, 1'b0, 1'b1, "LDR");

        check(6'b011011, 1'b0, 4'b0000, 2'b00, 2'b10, 1'b0, 1'b0, 1'b0, 1'b0, 1'b0, 1'b1, "JMP");

        check(6'b011100, 1'b1, 4'b0000, 2'b00, 2'b01, 1'b0, 1'b0, 1'b0, 1'b0, 1'b0, 1'b1, "BEQ taken");
        check(6'b011100, 1'b0, 4'b0000, 2'b00, 2'b00, 1'b0, 1'b0, 1'b0, 1'b0, 1'b0, 1'b0, "BEQ not taken");

        check(6'b011101, 1'b0, 4'b0000, 2'b00, 2'b01, 1'b0, 1'b0, 1'b0, 1'b0, 1'b0, 1'b1, "BNE taken");
        check(6'b011101, 1'b1, 4'b0000, 2'b00, 2'b00, 1'b0, 1'b0, 1'b0, 1'b0, 1'b0, 1'b0, "BNE not taken");

        check(6'b000000, 1'b0, 4'b0000, 2'b00, 2'b00, 1'b0, 1'b0, 1'b0, 1'b0, 1'b0, 1'b0, "illegal op group");
        check(6'b100010, 1'b0, 4'b0000, 2'b01, 2'b00, 1'b0, 1'b0, 1'b0, 1'b0, 1'b0, 1'b0, "illegal alu op");
        check(6'b010000, 1'b0, 4'b0000, 2'b00, 2'b00, 1'b0, 1'b0, 1'b0, 1'b0, 1'b0, 1'b0, "illegal class 01 op");

        $display("Control unit test completed");
        $finish;
    end

endmodule

Beta_Processor.sim/sim_1/behav/xsim/control_unit.vcd
$date
   Fri Jun 26 19:45:51 2026
$end

$version
  2024.2.0
  $dumpfile ("control_unit.vcd") 
$end

$timescale
  1ps
$end

$scope module tb_Control_unit $end
$var reg 1 ! z $end
$var reg 6 " op [5:0] $end
$var wire 4 # alufn [3:0] $end
$var wire 2 $ wdsel [1:0] $end
$var wire 2 % pcsel [1:0] $end
$var wire 1 & ra2sel $end
$var wire 1 ' asel $end
$var wire 1 ( bsel $end
$var wire 1 ) moe $end
$var wire 1 * mwr $end
$var wire 1 + werf $end
$scope module dut $end
$var wire 1 , z $end
$var wire 6 - op [5:0] $end
$var reg 4 . alufn [3:0] $end
$var reg 2 / wdsel [1:0] $end
$var reg 2 0 pcsel [1:0] $end
$var reg 1 1 ra2sel $end
$var reg 1 2 asel $end
$var reg 1 3 bsel $end
$var reg 1 4 moe $end
$var reg 1 5 mwr $end
$var reg 1 6 werf $end
$upscope $end
$scope task check $end
$var reg 6 7 op_in [5:0] $end
$var reg 1 8 z_in $end
$var reg 4 9 exp_alufn [3:0] $end
$var reg 2 : exp_wdsel [1:0] $end
$var reg 2 ; exp_pcsel [1:0] $end
$var reg 1 < exp_ra2sel $end
$var reg 1 = exp_asel $end
$var reg 1 > exp_bsel $end
$var reg 1 ? exp_moe $end
$var reg 1 @ exp_mwr $end
$var reg 1 A exp_werf $end
$var reg 161 B name [160:0] $end
$upscope $end
$upscope $end
$enddefinitions $end

#0
$dumpvars
0!
b100000 "
b0 #
b1 $
b0 %
0&
0'
0(
0)
0*
1+
0,
b100000 -
b0 .
b1 /
b0 0
01
02
03
04
05
16
b100000 7
08
b0 9
b1 :
b0 ;
0<
0=
0>
0?
0@
1A
b10000010100010001000100 B
$end

#10000
b100001 "
b1 #
b100001 -
b1 .
b1 /
16
b100001 7
b1 9
b10100110101010101000010 B

#20000
b100100 "
b100 #
b100100 -
b100 .
b1 /
16
b100100 7
b100 9
b100001101001101010100000100010101010001 B

#30000
b100101 "
b101 #
b100101 -
b101 .
b1 /
16
b100101 7
b101 9
b100001101001101010100000100110001010100 B

#40000
b100110 "
b110 #
b100110 -
b110 .
b1 /
16
b100110 7
b110 9
b100001101001101010100000100110001000101 B

#50000
b101000 "
b1000 #
b101000 -
b1000 .
b1 /
16
b101000 7
b1000 9
b10000010100111001000100 B

#60000
b101001 "
b1001 #
b101001 -
b1001 .
b1 /
16
b101001 7
b1001 9
b100111101010010 B

#70000
b101010 "
b1010 #
b101010 -
b1010 .
b1 /
16
b101010 7
b1010 9
b10110000100111101010010 B

#80000
b101011 "
b1011 #
b101011 -
b1011 .
b1 /
16
b101011 7
b1011 9
b1011000010011100100111101010010 B

#90000
b101100 "
b1100 #
b101100 -
b1100 .
b1 /
16
b101100 7
b1100 9
b10100110100100001001100 B

#100000
b101101 "
b1101 #
b101101 -
b1101 .
b1 /
16
b101101 7
b1101 9
b10100110100100001010010 B

#110000
b101111 "
b1111 #
b101111 -
b1111 .
b1 /
16
b101111 7
b1111 9
b10100110101001001000001 B

#120000
b110000 "
b0 #
1(
b110000 -
b0 .
b1 /
13
16
b110000 7
b0 9
1>
b1000001010001000100010001000011 B

#130000
b110001 "
b1 #
b110001 -
b1 .
b1 /
13
16
b110001 7
b1 9
b1010011010101010100001001000011 B

#140000
b111000 "
b1000 #
b111000 -
b1000 .
b1 /
13
16
b111000 7
b1000 9
b1000001010011100100010001000011 B

#150000
b111001 "
b1001 #
b111001 -
b1001 .
b1 /
13
16
b111001 7
b1001 9
b10011110101001001000011 B

#160000
b111010 "
b1010 #
b111010 -
b1010 .
b1 /
13
16
b111010 7
b1010 9
b1011000010011110101001001000011 B

#170000
b11000 "
b0 #
b10 $
1)
b11000 -
b0 .
b10 /
13
14
16
b11000 7
b0 9
b10 :
1?
b100110001000100 B

#180000
b11001 "
b0 $
1&
0)
1*
0+
b11001 -
b0 /
11
13
04
15
06
b11001 7
b0 :
1<
0?
1@
0A
b101001101010100 B

#190000
b11111 "
b10 $
0&
1'
1)
0*
1+
b11111 -
b10 /
01
12
13
14
05
16
b11111 7
b10 :
0<
1=
1?
0@
1A
b10011000100010001010010 B

#200000
b11011 "
b0 $
b10 %
0'
0(
0)
b11011 -
b0 /
b10 0
02
03
04
16
b11011 7
b0 :
b10 ;
0=
0>
0?
b10010100100110101010000 B

#210000
1!
b11100 "
b1 %
1,
b11100 -
b1 0
16
b11100 7
18
b1 ;
b10000100100010101010001001000000111010001100001011010110110010101101110 B

#220000
0!
b0 %
0+
0,
b0 0
06
08
b0 ;
0A
b1000010010001010101000100100000011011100110111101110100001000000111010001100001011010110110010101101110 B

#230000
b11101 "
b1 %
1+
b11101 -
b1 0
16
b11101 7
b1 ;
1A
b10000100100111001000101001000000111010001100001011010110110010101101110 B

#240000
1!
b0 %
0+
1,
b0 0
06
18
b0 ;
0A
b1000010010011100100010100100000011011100110111101110100001000000111010001100001011010110110010101101110 B

#250000
0!
b0 "
0,
b0 -
b0 7
08
b1101001011011000110110001100101011001110110000101101100001000000110111101110000001000000110011101110010011011110111010101110000 B

#260000
b100010 "
b1 $
b100010 -
b1 /
06
b100010 7
b1 :
b110100101101100011011000110010101100111011000010110110000100000011000010110110001110101001000000110111101110000 B

#270000
b10000 "
b0 $
b10000 -
b0 /
b10000 7
b0 :
b1101001011011000110110001100101011001110110000101101100001000000110001101101100011000010111001101110011001000000011000000110001001000000110111101110000 B
