Beta_Processor.srcs/sources_1/new/Data_memory.v
`timescale 1ns / 1ps
//////////////////////////////////////////////////////////////////////////////////
// Company: 
// Engineer: 
// 
// Create Date: 25.06.2026 19:17:37
// Design Name: 
// Module Name: Data_memory
// Project Name: 
// Target Devices: 
// Tool Versions: 
// Description: 
// 
// Dependencies: 
// 
// Revision:
// Revision 0.01 - File Created
// Additional Comments:
// 
//////////////////////////////////////////////////////////////////////////////////


module Data_memory(
    input  wire        clk,
    input  wire [31:0] WD,
    input  wire [31:0] Addr,
    input  wire        RW,
    input  wire        OE,
    output wire [31:0] RD
);

    reg [31:0] mem [0:1023];

    assign RD = (OE == 1'b1) ? mem[Addr] : 32'd0;

    always @(posedge clk) begin
        if (RW == 1'b1) begin
            mem[Addr] <= WD;
        end
    end

endmodule

Beta_Processor.srcs/sim_1/new/Data_memory_tb.v
`timescale 1ns / 1ps
//////////////////////////////////////////////////////////////////////////////////
// Company: 
// Engineer: 
// 
// Create Date: 25.06.2026 19:39:43
// Design Name: 
// Module Name: Data_memory_tb
// Project Name: 
// Target Devices: 
// Tool Versions: 
// Description: 
// 
// Dependencies: 
// 
// Revision:
// Revision 0.01 - File Created
// Additional Comments:
// 
//////////////////////////////////////////////////////////////////////////////////


`timescale 1ns/1ps


module tb_Data_memory;

    reg         clk;
    reg  [31:0] WD;
    reg  [31:0] Addr;
    reg         RW;
    reg         OE;
    wire [31:0] RD;

    Data_memory dut (
        .clk(clk),
        .WD(WD),
        .Addr(Addr),
        .RW(RW),
        .OE(OE),
        .RD(RD)
    );

    always #5 clk = ~clk;

    task check;
        input [31:0] actual;
        input [31:0] expected;
        input [160:0] name;
        begin
            if (actual !== expected)
                $display("FAIL: %s expected=%h got=%h", name, expected, actual);
            else
                $display("PASS: %s value=%h", name, actual);
        end
    endtask

    initial begin
        $dumpfile("data_memory.vcd");
        $dumpvars(0, tb_Data_memory);

        clk = 1'b0;
        WD = 32'd0;
        Addr = 32'd0;
        RW = 1'b0;
        OE = 1'b0;

        #1;
        check(RD, 32'h0000_0000, "OE low output zero");

        @(negedge clk);
        Addr = 32'd0;
        WD = 32'hAAAA_1111;
        RW = 1'b1;
        OE = 1'b0;

        @(posedge clk);
        #1;
        RW = 1'b0;
        OE = 1'b1;
        Addr = 32'd0;
        #1;
        check(RD, 32'hAAAA_1111, "read addr 0");

        @(negedge clk);
        Addr = 32'd1;
        WD = 32'hBBBB_2222;
        RW = 1'b1;
        OE = 1'b0;

        @(posedge clk);
        #1;
        RW = 1'b0;
        OE = 1'b1;
        Addr = 32'd1;
        #1;
        check(RD, 32'hBBBB_2222, "read addr 1");

        Addr = 32'd0;
        #1;
        check(RD, 32'hAAAA_1111, "addr 0 unchanged");

        @(negedge clk);
        Addr = 32'd2;
        WD = 32'hCCCC_3333;
        RW = 1'b1;
        OE = 1'b0;

        @(posedge clk);
        #1;
        RW = 1'b0;
        OE = 1'b1;
        Addr = 32'd2;
        #1;
        check(RD, 32'hCCCC_3333, "read addr 2");

        @(negedge clk);
        Addr = 32'd1;
        WD = 32'h1234_5678;
        RW = 1'b1;
        OE = 1'b0;

        @(posedge clk);
        #1;
        RW = 1'b0;
        OE = 1'b1;
        Addr = 32'd1;
        #1;
        check(RD, 32'h1234_5678, "overwrite addr 1");

        OE = 1'b0;
        #1;
        check(RD, 32'h0000_0000, "OE low hides data");

        OE = 1'b1;
        Addr = 32'd0;
        #1;
        check(RD, 32'hAAAA_1111, "comb read addr 0");

        Addr = 32'd1;
        #1;
        check(RD, 32'h1234_5678, "comb read addr 1");

        Addr = 32'd2;
        #1;
        check(RD, 32'hCCCC_3333, "comb read addr 2");

        $display("Data memory test completed.");
        $finish;
    end

endmodule

Beta_Processor.sim/sim_1/behav/xsim/data_memory.vcd
$date
   Thu Jun 25 19:41:13 2026
$end

$version
  2024.2.0
  $dumpfile ("data_memory.vcd") 
$end

$timescale
  1ps
$end

$scope module tb_Data_memory $end
$var reg 1 ! clk $end
$var reg 32 " WD [31:0] $end
$var reg 32 # Addr [31:0] $end
$var reg 1 $ RW $end
$var reg 1 % OE $end
$var wire 32 & RD [31:0] $end
$scope module dut $end
$var wire 1 ' clk $end
$var wire 32 ( WD [31:0] $end
$var wire 32 ) Addr [31:0] $end
$var wire 1 * RW $end
$var wire 1 + OE $end
$var wire 32 & RD [31:0] $end
$upscope $end
$scope task check $end
$var reg 32 , actual [31:0] $end
$var reg 32 - expected [31:0] $end
$var reg 161 . name [160:0] $end
$upscope $end
$upscope $end
$enddefinitions $end

#0
$dumpvars
0!
b0 "
b0 #
0$
0%
b0 &
0'
b0 (
b0 )
0*
0+
bx ,
bx -
bx .
$end

#1000
b0 ,
b0 -
b10011110100010100100000011011000110111101110111001000000110111101110101011101000111000001110101011101000010000001111010011001010111001001101111 .

#5000
1!
1'

#10000
0!
b10101010101010100001000100010001 "
1$
0'
b10101010101010100001000100010001 (
1*

#15000
1!
1'

#16000
0$
1%
b10101010101010100001000100010001 &
0*
1+

#17000
b10101010101010100001000100010001 ,
b10101010101010100001000100010001 -
b111001001100101011000010110010000100000011000010110010001100100011100100010000000110000 .

#20000
0!
b10111011101110110010001000100010 "
b1 #
1$
0%
b0 &
0'
b10111011101110110010001000100010 (
b1 )
1*
0+

#25000
1!
1'

#26000
0$
1%
b10111011101110110010001000100010 &
0*
1+

#27000
b0 #
b10101010101010100001000100010001 &
b0 )
b10111011101110110010001000100010 ,
b10111011101110110010001000100010 -
b111001001100101011000010110010000100000011000010110010001100100011100100010000000110001 .

#28000
b10101010101010100001000100010001 ,
b10101010101010100001000100010001 -
b1100001011001000110010001110010001000000011000000100000011101010110111001100011011010000110000101101110011001110110010101100100 .

#30000
0!
b11001100110011000011001100110011 "
b10 #
1$
0%
b0 &
0'
b11001100110011000011001100110011 (
b10 )
1*
0+

#35000
1!
1'

#36000
0$
1%
b11001100110011000011001100110011 &
0*
1+

#37000
b11001100110011000011001100110011 ,
b11001100110011000011001100110011 -
b111001001100101011000010110010000100000011000010110010001100100011100100010000000110010 .

#40000
0!
b10010001101000101011001111000 "
b1 #
1$
0%
b0 &
0'
b10010001101000101011001111000 (
b1 )
1*
0+

#45000
1!
1'

#46000
0$
1%
b10010001101000101011001111000 &
0*
1+

#47000
0%
b0 &
0+
b10010001101000101011001111000 ,
b10010001101000101011001111000 -
b1101111011101100110010101110010011101110111001001101001011101000110010100100000011000010110010001100100011100100010000000110001 .

#48000
b0 #
1%
b10101010101010100001000100010001 &
b0 )
1+
b0 ,
b0 -
b100111101000101001000000110110001101111011101110010000001101000011010010110010001100101011100110010000001100100011000010111010001100001 .

#49000
b1 #
b10010001101000101011001111000 &
b1 )
b10101010101010100001000100010001 ,
b10101010101010100001000100010001 -
b1100011011011110110110101100010001000000111001001100101011000010110010000100000011000010110010001100100011100100010000000110000 .

#50000
0!
b10 #
b11001100110011000011001100110011 &
0'
b10 )
b10010001101000101011001111000 ,
b10010001101000101011001111000 -
b1100011011011110110110101100010001000000111001001100101011000010110010000100000011000010110010001100100011100100010000000110001 .

#51000
b11001100110011000011001100110011 ,
b11001100110011000011001100110011 -
b1100011011011110110110101100010001000000111001001100101011000010110010000100000011000010110010001100100011100100010000000110010 .
