src/Register_file.v
`timescale 1ns / 1ps
//////////////////////////////////////////////////////////////////////////////////
// Company: 
// Engineer: 
// 
// Create Date: 25.06.2026 18:47:39
// Design Name: 
// Module Name: Register_file
// Project Name: 
// Target Devices: 
// Tool Versions: 
// Description: 
// 
// Dependencies: 
// 
// Revision:
// Revision 0.01 - File Created
// Additional Comments:
// 
//////////////////////////////////////////////////////////////////////////////////


module Register_file(
    input  wire        clk,
    input  wire [4:0]  RA1,
    input  wire [4:0]  RA2,
    input  wire [4:0]  WA,
    input  wire        WE,
    input  wire [31:0] WD,
    output wire [31:0] RD1,
    output wire [31:0] RD2
);

    reg [31:0] RF [0:31];

    assign RD1 = (RA1 == 5'd31) ? 32'b0 : RF[RA1];
    assign RD2 = (RA2 == 5'd31) ? 32'b0 : RF[RA2];

    always @(posedge clk) begin
        if (WE && (WA != 5'd31)) begin
            RF[WA] <= WD;
        end
    end

endmodule

Beta_Processor.srcs/sim_1/new/Register_file_tb.v
`timescale 1ns / 1ps
//////////////////////////////////////////////////////////////////////////////////
// Company: 
// Engineer: 
// 
// Create Date: 25.06.2026 19:14:00
// Design Name: 
// Module Name: Register_file_tb
// Project Name: 
// Target Devices: 
// Tool Versions: 
// Description: 
// 
// Dependencies: 
// 
// Revision:
// Revision 0.01 - File Created
// Additional Comments:
// 
//////////////////////////////////////////////////////////////////////////////////


`timescale 1ns/1ps


module tb_Register_file;

    reg         clk;
    reg  [4:0] RA1;
    reg  [4:0] RA2;
    reg  [4:0] WA;
    reg        WE;
    reg  [31:0] WD;
    wire [31:0] RD1;
    wire [31:0] RD2;

    Register_file dut (
        .clk(clk),
        .RA1(RA1),
        .RA2(RA2),
        .WA(WA),
        .WE(WE),
        .WD(WD),
        .RD1(RD1),
        .RD2(RD2)
    );

    always #5 clk = ~clk;

    task check;
        input [31:0] actual;
        input [31:0] expected;
        input [160:0] test_name;
        begin
            if (actual !== expected) begin
                $display("FAIL: %s | expected = %h, got = %h", test_name, expected, actual);
            end else begin
                $display("PASS: %s | value = %h", test_name, actual);
            end
        end
    endtask

    initial begin
        $dumpfile("register_file.vcd");
        $dumpvars(0, tb_Register_file);

        clk = 0;
        RA1 = 0;
        RA2 = 0;
        WA  = 0;
        WE  = 0;
        WD  = 0;

        // Write 0xAAAA_1111 into R5
        @(negedge clk);
        WA = 5'd5;
        WD = 32'hAAAA_1111;
        WE = 1'b1;

        @(posedge clk);
        #1;
        WE = 1'b0;

        // Read R5 using port 1
        RA1 = 5'd5;
        #1;
        check(RD1, 32'hAAAA_1111, "Read R5 from RD1");

        // Write 0xBBBB_2222 into R6
        @(negedge clk);
        WA = 5'd6;
        WD = 32'hBBBB_2222;
        WE = 1'b1;

        @(posedge clk);
        #1;
        WE = 1'b0;

        // Read R5 and R6 together
        RA1 = 5'd5;
        RA2 = 5'd6;
        #1;
        check(RD1, 32'hAAAA_1111, "Read R5 from RD1 again");
        check(RD2, 32'hBBBB_2222, "Read R6 from RD2");

        // Check combinational read change without clock
        RA1 = 5'd6;
        #1;
        check(RD1, 32'hBBBB_2222, "Combinational read changes immediately");

        // Try writing with WE = 0, should not update R5
        @(negedge clk);
        WA = 5'd5;
        WD = 32'hDEAD_BEEF;
        WE = 1'b0;

        @(posedge clk);
        #1;

        RA1 = 5'd5;
        #1;
        check(RD1, 32'hAAAA_1111, "WE = 0, R5 should not change");

        // Try writing to R31, should be ignored
        @(negedge clk);
        WA = 5'd31;
        WD = 32'hFFFF_FFFF;
        WE = 1'b1;

        @(posedge clk);
        #1;
        WE = 1'b0;

        RA1 = 5'd31;
        RA2 = 5'd31;
        #1;
        check(RD1, 32'h0000_0000, "R31 always zero on RD1");
        check(RD2, 32'h0000_0000, "R31 always zero on RD2");

        // Read during write test
        @(negedge clk);
        WA  = 5'd7;
        WD  = 32'h1234_5678;
        RA1 = 5'd7;
        WE  = 1'b1;

        @(posedge clk);
        #1;
        WE = 1'b0;

        check(RD1, 32'h1234_5678, "Read same register after clocked write");

        $display("Register file test completed.");
        $finish;
    end

endmodule

Beta_Processor.sim/sim_1/behav/xsim/register_file.vcd
$date
   Thu Jun 25 19:16:02 2026
$end

$version
  2024.2.0
  $dumpfile ("register_file.vcd") 
$end

$timescale
  1ps
$end

$scope module tb_Register_file $end
$var reg 1 ! clk $end
$var reg 5 " RA1 [4:0] $end
$var reg 5 # RA2 [4:0] $end
$var reg 5 $ WA [4:0] $end
$var reg 1 % WE $end
$var reg 32 & WD [31:0] $end
$var wire 32 ' RD1 [31:0] $end
$var wire 32 ( RD2 [31:0] $end
$scope module dut $end
$var wire 1 ) clk $end
$var wire 5 * RA1 [4:0] $end
$var wire 5 + RA2 [4:0] $end
$var wire 5 , WA [4:0] $end
$var wire 1 - WE $end
$var wire 32 . WD [31:0] $end
$var wire 32 ' RD1 [31:0] $end
$var wire 32 ( RD2 [31:0] $end
$upscope $end
$scope task check $end
$var reg 32 / actual [31:0] $end
$var reg 32 0 expected [31:0] $end
$var reg 161 1 test_name [160:0] $end
$upscope $end
$upscope $end
$enddefinitions $end

#0
$dumpvars
0!
b0 "
b0 #
b0 $
0%
b0 &
bx '
bx (
0)
b0 *
b0 +
b0 ,
0-
b0 .
bx /
bx 0
bx 1
$end

#5000
1!
1)

#10000
0!
b101 $
1%
b10101010101010100001000100010001 &
0)
b101 ,
1-
b10101010101010100001000100010001 .

#15000
1!
1)

#16000
b101 "
0%
b10101010101010100001000100010001 '
b101 *
0-

#17000
b10101010101010100001000100010001 /
b10101010101010100001000100010001 0
b1010010011001010110000101100100001000000101001000110101001000000110011001110010011011110110110100100000010100100100010000110001 1

#20000
0!
b110 $
1%
b10111011101110110010001000100010 &
0)
b110 ,
1-
b10111011101110110010001000100010 .

#25000
1!
1)

#26000
b110 #
0%
b10111011101110110010001000100010 (
b110 +
0-

#27000
b110 "
b10111011101110110010001000100010 '
b110 *
b10111011101110110010001000100010 /
b10111011101110110010001000100010 0
b1010010011001010110000101100100001000000101001000110110001000000110011001110010011011110110110100100000010100100100010000110010 1

#28000
b10000001100011011010000110000101101110011001110110010101110011001000000110100101101101011011010110010101100100011010010110000101110100011001010110110001111001 1

#30000
0!
b101 $
b11011110101011011011111011101111 &
0)
b101 ,
b11011110101011011011111011101111 .

#35000
1!
1)

#36000
b101 "
b10101010101010100001000100010001 '
b101 *

#37000
b10101010101010100001000100010001 /
b10101010101010100001000100010001 0
b101001000110101001000000111001101101000011011110111010101101100011001000010000001101110011011110111010000100000011000110110100001100001011011100110011101100101 1

#40000
0!
b11111 $
1%
b11111111111111111111111111111111 &
0)
b11111 ,
1-
b11111111111111111111111111111111 .

#45000
1!
1)

#46000
b11111 "
b11111 #
0%
b0 '
b0 (
b11111 *
b11111 +
0-

#47000
b0 /
b0 0
b10011000100100000011000010110110001110111011000010111100101110011001000000111101001100101011100100110111100100000011011110110111000100000010100100100010000110010 1

#50000
0!
b111 "
b111 $
1%
b10010001101000101011001111000 &
bx '
0)
b111 *
b111 ,
1-
b10010001101000101011001111000 .

#55000
1!
b10010001101000101011001111000 '
1)

#56000
0%
b10010001101000101011001111000 /
b10010001101000101011001111000 0
b10000001100001011001100111010001100101011100100010000001100011011011000110111101100011011010110110010101100100001000000111011101110010011010010111010001100101 1
